tmeragflow_mcp_server/__init__.py
tmeragflow_mcp_server/config.py
tmeragflow_mcp_server/server.py
tmeragflow_mcp_server-0.1.7.dist-info/METADATA
tmeragflow_mcp_server-0.1.7.dist-info/WHEEL
tmeragflow_mcp_server-0.1.7.dist-info/entry_points.txt
tmeragflow_mcp_server-0.1.7.dist-info/RECORD
