Metadata-Version: 2.4
Name: tmeragflow-mcp-server
Version: 0.1.7
Summary: RAGFlow MCP Server - A Model Context Protocol server integrating with RAGFlow APIs
Author-email: larryllin <larryllin@tencent.com>
Requires-Python: >=3.10
Requires-Dist: click>=8.1.8
Requires-Dist: mcp>=1.6.0
Requires-Dist: python-dotenv>=1.1.0
Requires-Dist: ragflow-sdk>=0.17.2
